<?xml version="1.0" encoding="utf-8"?>
<ImportExportXml xmlns:xsi="http://www.w3.org/2001/XMLSchema-instance" OrganizationVersion="9.2.25063.176" OrganizationSchemaType="Standard" CRMServerServiceabilityVersion="9.2.25063.00176">
  <Entities />
  <Roles />
  <Workflows />
  <FieldSecurityProfiles />
  <Templates />
  <EntityMaps />
  <EntityRelationships />
  <OrganizationSettings />
  <optionsets />
  <Dashboards />
  <CustomControls />
  <EntityDataProviders />
  <CanvasApps />
  <connectionreferences>
    <connectionreference connectionreferencelogicalname="new_sharedoffice365_10591">
      <connectionreferencedisplayname>Office 365 Outlook Default-10591</connectionreferencedisplayname>
      <connectorid>/providers/Microsoft.PowerApps/apis/shared_office365</connectorid>
      <iscustomizable>1</iscustomizable>
      <promptingbehavior>0</promptingbehavior>
      <statecode>0</statecode>
      <statuscode>1</statuscode>
    </connectionreference>
    <connectionreference connectionreferencelogicalname="new_sharedpowerbi_958eb">
      <connectionreferencedisplayname>Power BI Default-958eb</connectionreferencedisplayname>
      <connectorid>/providers/Microsoft.PowerApps/apis/shared_powerbi</connectorid>
      <iscustomizable>1</iscustomizable>
      <promptingbehavior>0</promptingbehavior>
      <statecode>0</statecode>
      <statuscode>1</statuscode>
    </connectionreference>
  </connectionreferences>
  <Languages>
    <Language>1033</Language>
  </Languages>
</ImportExportXml>